git_assume/__init__.py
git_assume/logger_config.yml
git_assume/main.py
git_assume/utils.py
git_assume/subcommands/subcommand_assume.py
git_assume/subcommands/subcommand_list.py
git_assume-1.0.3.dist-info/METADATA
git_assume-1.0.3.dist-info/WHEEL
git_assume-1.0.3.dist-info/entry_points.txt
git_assume-1.0.3.dist-info/licenses/LICENSE.txt
git_assume-1.0.3.dist-info/RECORD
