Metadata-Version: 2.3
Name: git-assume
Version: 1.0.3
Summary: Add your description here
Author-email: Josuke YAMANE <s1r0mqme@gmail.com>
License-File: LICENSE.txt
Requires-Python: >=3.8
Requires-Dist: pyyaml>=6.0.2
